corva_otel/semconv/__init__.py
corva_otel/semconv/attributes.py
corva_otel/semconv/corva_semattrs.py
corva_otel/semconv/corva_streamx_semattrs.py
corva_otel/semconv/streamx.py
corva_otel_semconv-0.2.0.dist-info/METADATA
corva_otel_semconv-0.2.0.dist-info/WHEEL
corva_otel_semconv-0.2.0.dist-info/RECORD
